gumbelcodes/__init__.py
gumbelcodes/models/__init__.py
gumbelcodes/models/keyedvectors.py
gumbelcodes/models/sentiment.py
gumbelcodes/nncompress/__init__.py
gumbelcodes/nncompress/embed_compress.py
gumbelcodes/nncompress/pipeline.py
gumbelcodes/utils/__init__.py
gumbelcodes/utils/fileutils.py
gumbelcodes/utils/matutils.py
gumbelcodes-0.9.dist-info/METADATA
gumbelcodes-0.9.dist-info/WHEEL
gumbelcodes-0.9.dist-info/top_level.txt
gumbelcodes-0.9.dist-info/RECORD
