Metadata-Version: 2.1
Name: gumbelcodes
Version: 0.9
Summary: Neural compression for word embeddings
Home-page: https://github.com/ruanchaves/gumbelcodes
Author: Ruan Chaves Rodrigues
Author-email: ruanchaves93@gmail.com
License: MIT
Keywords: NLP embeddings compression
Platform: UNKNOWN
Classifier: License :: OSI Approved :: MIT License
Classifier: Programming Language :: Python :: 3.6
Classifier: Topic :: Text Processing :: Linguistic
Requires-Dist: aiocontextvars (==0.2.2)
Requires-Dist: contextvars (==2.4)
Requires-Dist: immutables (==0.11)
Requires-Dist: loguru (==0.4.0)
Requires-Dist: marisa-trie (==0.7.5)
Requires-Dist: numpy (==1.18.0)
Requires-Dist: scipy (==1.4.1)
Requires-Dist: six (==1.13.0)
Provides-Extra: training
Requires-Dist: absl-py (==0.9.0) ; extra == 'training'
Requires-Dist: astor (==0.8.1) ; extra == 'training'
Requires-Dist: gast (==0.3.2) ; extra == 'training'
Requires-Dist: google-pasta (==0.1.8) ; extra == 'training'
Requires-Dist: grpcio (==1.26.0) ; extra == 'training'
Requires-Dist: h5py (==2.10.0) ; extra == 'training'
Requires-Dist: Keras-Applications (==1.0.8) ; extra == 'training'
Requires-Dist: Keras-Preprocessing (==1.1.0) ; extra == 'training'
Requires-Dist: Markdown (==3.1.1) ; extra == 'training'
Requires-Dist: protobuf (==3.11.2) ; extra == 'training'
Requires-Dist: tensorboard (==1.14.0) ; extra == 'training'
Requires-Dist: tensorflow-estimator (==1.14.0) ; extra == 'training'
Requires-Dist: tensorflow-gpu (==1.14.0) ; extra == 'training'
Requires-Dist: termcolor (==1.1.0) ; extra == 'training'
Requires-Dist: Werkzeug (==0.16.0) ; extra == 'training'
Requires-Dist: wrapt (==1.11.2) ; extra == 'training'
